fleascope_live_display/__init__.py
fleascope_live_display/device_config_ui.py
fleascope_live_display/fleascope_adapter.py
fleascope_live_display/live_display.py
fleascope_live_display/toasts.py
fleascope_live_display/pyfleascope/pyfleascope/__init__.py
fleascope_live_display/pyfleascope/pyfleascope/flea_scope.py
fleascope_live_display/pyfleascope/pyfleascope/serial_terminal.py
fleascope_live_display/pyfleascope/pyfleascope/trigger_config.py
fleascope_live_display-0.0.11.dist-info/METADATA
fleascope_live_display-0.0.11.dist-info/WHEEL
fleascope_live_display-0.0.11.dist-info/entry_points.txt
fleascope_live_display-0.0.11.dist-info/RECORD
