Metadata-Version: 2.4
Name: fleascope-live-display
Version: 0.0.11
Summary: Oscilloscope frontend for FleaScope
Project-URL: Homepage, https://github.com/daniel-freiermuth/fleascope-live
Project-URL: Issues, https://github.com/daniel-freiermuth/fleascope-live/issues
Author-email: "D. Freiermuth" <author@example.com>
License-Expression: MIT
Classifier: Operating System :: OS Independent
Classifier: Programming Language :: Python :: 3
Requires-Python: >=3.9
Requires-Dist: pyfleascope>=0.1.0
Requires-Dist: pyqt6
Requires-Dist: pyqtgraph
